dguslib/__init__.py
dguslib/data_packs.py
dguslib/dgus.py
dguslib/graphic_commands.py
dguslib/helpers.py
dguslib/version.py
dguslib/configuration/__init__.py
dguslib/configuration/configs.py
dguslib/configuration/descriptors.py
trimarlib_dgus-0.1.0a1.dist-info/METADATA
trimarlib_dgus-0.1.0a1.dist-info/RECORD
trimarlib_dgus-0.1.0a1.dist-info/WHEEL
trimarlib_dgus-0.1.0a1.dist-info/top_level.txt
