Metadata-Version: 2.1
Name: trimarlib-dgus
Version: 0.1.0a1
Summary: DWIN DGUS display utility library
Home-page: https://dsl2.trimar.org/pythons/dguslib
Author: Kacper Kubkowski
Author-email: k.kubkowski@trimar.com.pl
License: UNKNOWN
Platform: UNKNOWN
Classifier: Development Status :: 1 - Planning
Classifier: Intended Audience :: Developers
Classifier: License :: OSI Approved :: MIT License
Classifier: Natural Language :: English
Classifier: Operating System :: POSIX :: Linux
Classifier: Programming Language :: Python :: 3 :: Only
Classifier: Programming Language :: Python :: Implementation :: CPython
Classifier: Topic :: Software Development :: Embedded Systems
Requires-Dist: pyserial
Requires-Dist: webcolors
Requires-Dist: crcmod
